bbs/__init__.py
bbs/__main__.py
bbs/config.py
bbs/core.py
bbs/extensionbase.py
bbs/ext/boards/__init__.py
bbs/ext/boards/config.py
bbs/ext/boards/crud.py
bbs/ext/boards/models.py
bbs/ext/boards/routes.py
bbs/ext/boards/schemas.py
bbs/ext/users/__init__.py
bbs/ext/users/config.py
bbs/ext/users/crud.py
bbs/ext/users/models.py
bbs/ext/users/routes.py
bbs/ext/users/schemas.py
bbs/utils/pydantic_sqlalchemy.py
nubbs-0.0.1.dist-info/LICENSE.txt
nubbs-0.0.1.dist-info/METADATA
nubbs-0.0.1.dist-info/WHEEL
nubbs-0.0.1.dist-info/entry_points.txt
nubbs-0.0.1.dist-info/top_level.txt
nubbs-0.0.1.dist-info/RECORD
