Metadata-Version: 2.1
Name: nubbs
Version: 0.0.1
Summary: bbs api
Home-page: https://github.com/pyscaffold/pyscaffold/
Author: Iacchus Mercurius
Author-email: kassivs+git@gmail.com
License: MIT
Project-URL: Documentation, https://pyscaffold.org/
Platform: any
Classifier: Development Status :: 4 - Beta
Classifier: Programming Language :: Python
License-File: LICENSE.txt
Requires-Dist: click
Requires-Dist: fastapi
Requires-Dist: pydantic
Requires-Dist: starlette
Requires-Dist: toml
Provides-Extra: testing
Requires-Dist: setuptools ; extra == 'testing'
Requires-Dist: pytest ; extra == 'testing'
Requires-Dist: pytest-cov ; extra == 'testing'
